csvgen/__init__.py
csvgen/__main__.py
csvgen/generator.py
csvgen/random_utils.py
ombrocsv-1.0.0.dist-info/LICENSE
ombrocsv-1.0.0.dist-info/METADATA
ombrocsv-1.0.0.dist-info/WHEEL
ombrocsv-1.0.0.dist-info/entry_points.txt
ombrocsv-1.0.0.dist-info/top_level.txt
ombrocsv-1.0.0.dist-info/RECORD
