Metadata-Version: 2.1
Name: ombrocsv
Version: 1.0.0
Summary: Generate random CSV files
Home-page: https://github.com/SudoOmbro/csv-gen
Author: SudoOmbro
Author-email: ombroso1000@gmail.com
License: MIT
Platform: UNKNOWN
Classifier: License :: OSI Approved :: MIT License
Classifier: Programming Language :: Python :: 3
Classifier: Programming Language :: Python :: 3.9
License-File: LICENSE
